{
    "actions": [
        {
            "actors": ["A"],
            "urn": "urn:centipede:take",
            "name": "Take",
            "id": "d44cc237-9e09-4cb9-97aa-6f32831df844",
            "inputs": [
                { "name": "turn", "type": "int", "value": 0 },
                { "name": "pot", "type": "int", "value": 5 }
            ],
            "outputs": [
                { "name": "game_over", "type": "boolean" },
                { "name": "payoff", "type": "int" }
            ],
            "expected_cost": null,
            "expected_value": { "payoff": 4 }
        },
        {
            "actors": ["A"],
            "urn": "urn:centipede:push",
            "name": "Push",
            "id": "bf93c4cc-6063-458e-afa4-b024f5c9abb6",
            "inputs": [
                { "name": "turn", "type": "int", "value": 0 },
                { "name": "pot", "type": "int", "value": 5 }
            ],
            "outputs": [
                { "name": "game_over", "type": "boolean" },
                { "name": "payoff", "type": "int" },
                { "name": "new_pot", "type": "int" }
            ],
            "expected_cost": null,
            "expected_value": null
        }
    ]
}
